Metadata-Version: 2.1
Name: classes-farrukh90
Version: 0.0.33
Summary: This is used to check tasks
Home-page: https://github.com/pypa/sampleproject
Author: Farrukh Sadykov
Author-email: farrukhsadykov@gmail.com
License: UNKNOWN
Project-URL: Bug Tracker, https://github.com/pypa/sampleproject/issues
Platform: UNKNOWN
Classifier: Programming Language :: Python :: 3
Classifier: License :: OSI Approved :: MIT License
Classifier: Operating System :: OS Independent
Requires-Python: >=3.6
License-File: LICENSE
